intake_cs109b_data_mma/__init__.py
intake_cs109b_data_mma/nested_catalog.yaml
intake_cs109b_data_mma-0.0.4.dist-info/METADATA
intake_cs109b_data_mma-0.0.4.dist-info/WHEEL
intake_cs109b_data_mma-0.0.4.dist-info/entry_points.txt
intake_cs109b_data_mma-0.0.4.dist-info/top_level.txt
intake_cs109b_data_mma-0.0.4.dist-info/RECORD
