Metadata-Version: 2.1
Name: intake-cs109b-data-mma
Version: 0.0.4
Summary: Data for cs109b group project, Spring2020
Home-page: UNKNOWN
Author: UNKNOWN
Author-email: UNKNOWN
License: UNKNOWN
Platform: UNKNOWN
Requires-Dist: intake
Requires-Dist: intake-nested-yaml-catalog
